{"stats":{"minecraft:mined":{"minecraft:beetroots":12,"minecraft:melon":1,"minecraft:grass_block":2,"minecraft:wheat":9,"minecraft:carrots":12,"minecraft:cave_vines_plant":2,"minecraft:sugar_cane":2,"minecraft:white_bed":3,"minecraft:short_grass":2,"minecraft:yellow_bed":1,"minecraft:oak_leaves":3,"minecraft:poppy":1,"minecraft:potatoes":4,"minecraft:composter":1,"minecraft:cave_vines":1},"minecraft:picked_up":{"minecraft:yellow_bed":1,"minecraft:carrot":50,"minecraft:dirt":2,"minecraft:saddle":1,"minecraft:composter":1,"minecraft:white_bed":3,"minecraft:sugar_cane":3,"minecraft:leaf_litter":2,"minecraft:glow_berries":1,"minecraft:cooked_cod":2,"minecraft:potato":35,"minecraft:melon_slice":5,"minecraft:wheat_seeds":19,"minecraft:porkchop":3,"minecraft:ink_sac":2,"minecraft:salmon":4,"minecraft:oak_trapdoor":1,"minecraft:poppy":1,"minecraft:cooked_beef":3,"minecraft:white_wool":2,"minecraft:feather":2,"minecraft:chicken":1,"minecraft:rotten_flesh":2,"minecraft:beetroot_seeds":34,"minecraft:wheat":9,"minecraft:mutton":4,"minecraft:gunpowder":2,"minecraft:beetroot":12},"minecraft:custom":{"minecraft:talked_to_villager":4,"minecraft:time_since_rest":11443,"minecraft:walk_one_cm":132732,"minecraft:leave_game":6,"minecraft:horse_one_cm":805226,"minecraft:walk_under_water_one_cm":6028,"minecraft:mob_kills":9,"minecraft:damage_taken":123,"minecraft:play_time":64411,"minecraft:damage_dealt":552,"minecraft:jump":347,"minecraft:time_since_death":64411,"minecraft:sprint_one_cm":131284,"minecraft:open_chest":9,"minecraft:sleep_in_bed":3,"minecraft:fall_one_cm":12098,"minecraft:total_world_time":64411,"minecraft:swim_one_cm":14938,"minecraft:fly_one_cm":53346,"minecraft:walk_on_water_one_cm":9571,"minecraft:crouch_one_cm":23723,"minecraft:sneak_time":6520,"minecraft:climb_one_cm":8},"minecraft:killed":{"minecraft:salmon":4,"minecraft:chicken":1,"minecraft:pig":1,"minecraft:sheep":2,"minecraft:squid":1},"minecraft:used":{"minecraft:stone_axe":10,"minecraft:oak_trapdoor":1,"minecraft:stone_sword":33,"minecraft:cooked_beef":2,"minecraft:yellow_bed":1,"minecraft:white_bed":2,"minecraft:dirt":2,"minecraft:cooked_cod":2}},"DataVersion":4556}